iqoption_async/__init__.py
iqoption_async/api.py
iqoption_async/client.py
iqoption_async/constants.py
iqoption_async/expiration.py
iqoption_async/version_control.py
iqoption_async/http/__init__.py
iqoption_async/http/resource.py
iqoption_async/ws/__init__.py
iqoption_async/ws/client.py
iqoption_async/ws/channels/__init__.py
iqoption_async/ws/channels/base.py
iqoption_async/ws/objects/__init__.py
iqoption_async/ws/objects/candles.py
iqoption_async/ws/objects/profile.py
iqoption_async/ws/objects/time_sync.py
iqoption_async/ws/received/__init__.py
iqoption_async/ws/received/balances.py
iqoption_async/ws/received/candles.py
iqoption_async/ws/received/initialization_data.py
iqoption_async/ws/received/option.py
iqoption_async/ws/received/position_changed.py
iqoption_async/ws/received/profile.py
iqoption_async/ws/received/result.py
iqoption_async/ws/received/time_sync.py
tests/__init__.py
iqoption_async-0.0.1.dist-info/LICENSE
iqoption_async-0.0.1.dist-info/METADATA
iqoption_async-0.0.1.dist-info/WHEEL
iqoption_async-0.0.1.dist-info/top_level.txt
iqoption_async-0.0.1.dist-info/RECORD
