Metadata-Version: 2.1
Name: iqoption-async
Version: 0.0.1
Summary: An updated Python library for interacting with IQ Option using asyncio and modern WebSockets.
Home-page: https://github.com/s00rk/iqoption_async
Author: Victor Rivera
Author-email: victor.riverac92@gmail.com
Keywords: iqoption trading api asyncio websockets
Classifier: Development Status :: 3 - Alpha
Classifier: Intended Audience :: Developers
Classifier: License :: OSI Approved :: MIT License
Classifier: Programming Language :: Python :: 3.11
Classifier: Programming Language :: Python :: 3.12
Requires-Python: >=3.11
License-File: LICENSE
